LICENSE
MANIFEST.in
README.rst
mongo_mail_server.py
setup.cfg
setup.py
mongo_mail_server.egg-info/PKG-INFO
mongo_mail_server.egg-info/SOURCES.txt
mongo_mail_server.egg-info/dependency_links.txt
mongo_mail_server.egg-info/entry_points.txt
mongo_mail_server.egg-info/not-zip-safe
mongo_mail_server.egg-info/pbr.json
mongo_mail_server.egg-info/requires.txt
mongo_mail_server.egg-info/top_level.txt