Metadata-Version: 1.1
Name: mongo-mail-server
Version: 0.1.0
Summary: Python SMTP server with Gevent for recording messages in MongoDB
Home-page: https://github.com/srault95/mongo-mail-server
Author: Stéphane RAULT
Author-email: stephane.rault@radicalspam.org
License: BSD
Platform: UNKNOWN
Classifier: Topic :: Communications :: Email
Classifier: Topic :: Communications :: Email :: Mail Transport Agents
Classifier: Development Status :: 4 - Beta
Classifier: Operating System :: POSIX :: Linux
Classifier: Programming Language :: Python
Classifier: Programming Language :: Python :: 2
Classifier: Programming Language :: Python :: 2.7
Classifier: License :: OSI Approved :: BSD License
Classifier: Intended Audience :: Developers
Classifier: Intended Audience :: System Administrators
